dyn_plot/__init__.py
dyn_plot-0.1.1.dist-info/LICENSE
dyn_plot-0.1.1.dist-info/METADATA
dyn_plot-0.1.1.dist-info/WHEEL
dyn_plot-0.1.1.dist-info/RECORD
