Metadata-Version: 2.1
Name: dyn-plot
Version: 0.1.1
Summary: Dynamic matplotlib plots in Jupyter notebooks
License: Apache-2.0
Author: Cristian Garcia
Author-email: cgarcia.e88@gmail.com
Requires-Python: >=3.9,<4
Classifier: License :: OSI Approved :: Apache Software License
Classifier: Programming Language :: Python :: 3
Classifier: Programming Language :: Python :: 3.9
Classifier: Programming Language :: Python :: 3.10
Classifier: Programming Language :: Python :: 3.11
Classifier: Programming Language :: Python :: 3.12
Requires-Dist: matplotlib (>=2)
